{"created_at": "Wed Feb 27 15:37:38 +0000 2019", "id": 1100782012909023233, "id_str": "1100782012909023233", "full_text": "RT @MirAliAsgar: Modi has given us a good hiding of d truth since 2k14. 5 yrs of ruse n fallacies. Unfortunate is d 300 kgs of RDX brought\u2026", "truncated": false, "display_text_range": [0, 139], "entities": {"hashtags": [], "symbols": [], "user_mentions": [{"screen_name": "MirAliAsgar", "name": "Mir Ali Asgar", "id": 79941708, "id_str": "79941708", "indices": [3, 15]}], "urls": []}, "metadata": {"iso_language_code": "en", "result_type": "recent"}, "source": "<a href=\"http://twitter.com/download/android\" rel=\"nofollow\">Twitter for Android</a>", "in_reply_to_status_id": null, "in_reply_to_status_id_str": null, "in_reply_to_user_id": null, "in_reply_to_user_id_str": null, "in_reply_to_screen_name": null, "user": {"id": 2233246706, "id_str": "2233246706", "name": "Dr. J Aslam Basha", "screen_name": "JAslamBasha", "location": "India", "description": "Chairman - Minority Department Tamil Nadu Congress Committee | AICC Member | National Chairman Shri @NadeemINC | Advocate | Views Are Personal | Jai Hind", "url": "https://t.co/LSenSwxndL", "entities": {"url": {"urls": [{"url": "https://t.co/LSenSwxndL", "expanded_url": "http://tnccminority.com", "display_url": "tnccminority.com", "indices": [0, 23]}]}, "description": {"urls": []}}, "protected": false, "followers_count": 8827, "friends_count": 207, "listed_count": 86, "created_at": "Fri Dec 06 16:44:14 +0000 2013", "favourites_count": 66965, "utc_offset": null, "time_zone": null, "geo_enabled": false, "verified": true, "statuses_count": 87334, "lang": "en", "contributors_enabled": false, "is_translator": false, "is_translation_enabled": false, "profile_background_color": "000000", "profile_background_image_url": "http://abs.twimg.com/images/themes/theme1/bg.png", "profile_background_image_url_https": "https://abs.twimg.com/images/themes/theme1/bg.png", "profile_background_tile": false, "profile_image_url": "http://pbs.twimg.com/profile_images/1089106854322495488/sWQrQB9N_normal.jpg", "profile_image_url_https": "https://pbs.twimg.com/profile_images/1089106854322495488/sWQrQB9N_normal.jpg", "profile_banner_url": "https://pbs.twimg.com/profile_banners/2233246706/1502507556", "profile_link_color": "1B95E0", "profile_sidebar_border_color": "000000", "profile_sidebar_fill_color": "000000", "profile_text_color": "000000", "profile_use_background_image": false, "has_extended_profile": true, "default_profile": false, "default_profile_image": false, "following": false, "follow_request_sent": false, "notifications": false, "translator_type": "none"}, "geo": null, "coordinates": null, "place": null, "contributors": null, "retweeted_status": {"created_at": "Wed Feb 27 11:20:47 +0000 2019", "id": 1100717378231402497, "id_str": "1100717378231402497", "full_text": "Modi has given us a good hiding of d truth since 2k14. 5 yrs of ruse n fallacies. Unfortunate is d 300 kgs of RDX brought into #Pulwama by JeM which claimed 40 lives of CRPF. This failure alone is enough for d ppl not 2 bring back BJP to power in 2k19. @RahulGandhi @JAslamBasha https://t.co/8OYjasMB0W", "truncated": false, "display_text_range": [0, 278], "entities": {"hashtags": [{"text": "Pulwama", "indices": [127, 135]}], "symbols": [], "user_mentions": [{"screen_name": "RahulGandhi", "name": "Rahul Gandhi", "id": 3171712086, "id_str": "3171712086", "indices": [253, 265]}, {"screen_name": "JAslamBasha", "name": "Dr. J Aslam Basha", "id": 2233246706, "id_str": "2233246706", "indices": [266, 278]}], "urls": [], "media": [{"id": 1100717363685511168, "id_str": "1100717363685511168", "indices": [279, 302], "media_url": "http://pbs.twimg.com/media/D0aInESUUAA0ep-.jpg", "media_url_https": "https://pbs.twimg.com/media/D0aInESUUAA0ep-.jpg", "url": "https://t.co/8OYjasMB0W", "display_url": "pic.twitter.com/8OYjasMB0W", "expanded_url": "https://twitter.com/MirAliAsgar/status/1100717378231402497/photo/1", "type": "photo", "sizes": {"medium": {"w": 1200, "h": 1200, "resize": "fit"}, "small": {"w": 680, "h": 680, "resize": "fit"}, "thumb": {"w": 150, "h": 150, "resize": "crop"}, "large": {"w": 2036, "h": 2036, "resize": "fit"}}}]}, "extended_entities": {"media": [{"id": 1100717363685511168, "id_str": "1100717363685511168", "indices": [279, 302], "media_url": "http://pbs.twimg.com/media/D0aInESUUAA0ep-.jpg", "media_url_https": "https://pbs.twimg.com/media/D0aInESUUAA0ep-.jpg", "url": "https://t.co/8OYjasMB0W", "display_url": "pic.twitter.com/8OYjasMB0W", "expanded_url": "https://twitter.com/MirAliAsgar/status/1100717378231402497/photo/1", "type": "photo", "sizes": {"medium": {"w": 1200, "h": 1200, "resize": "fit"}, "small": {"w": 680, "h": 680, "resize": "fit"}, "thumb": {"w": 150, "h": 150, "resize": "crop"}, "large": {"w": 2036, "h": 2036, "resize": "fit"}}}]}, "metadata": {"iso_language_code": "en", "result_type": "recent"}, "source": "<a href=\"http://twitter.com/download/android\" rel=\"nofollow\">Twitter for Android</a>", "in_reply_to_status_id": null, "in_reply_to_status_id_str": null, "in_reply_to_user_id": null, "in_reply_to_user_id_str": null, "in_reply_to_screen_name": null, "user": {"id": 79941708, "id_str": "79941708", "name": "Mir Ali Asgar", "screen_name": "MirAliAsgar", "location": "Chennai | India", "description": "Indian National Congress | Imam Hussain Helpline | Social Activist Maran Law Chambers | International Political Observer", "url": null, "entities": {"description": {"urls": []}}, "protected": false, "followers_count": 55, "friends_count": 88, "listed_count": 0, "created_at": "Mon Oct 05 06:26:13 +0000 2009", "favourites_count": 55, "utc_offset": null, "time_zone": null, "geo_enabled": true, "verified": false, "statuses_count": 106, "lang": "en", "contributors_enabled": false, "is_translator": false, "is_translation_enabled": false, "profile_background_color": "C0DEED", "profile_background_image_url": "http://abs.twimg.com/images/themes/theme1/bg.png", "profile_background_image_url_https": "https://abs.twimg.com/images/themes/theme1/bg.png", "profile_background_tile": false, "profile_image_url": "http://pbs.twimg.com/profile_images/1040110457892167680/OSuteJ7w_normal.jpg", "profile_image_url_https": "https://pbs.twimg.com/profile_images/1040110457892167680/OSuteJ7w_normal.jpg", "profile_link_color": "1DA1F2", "profile_sidebar_border_color": "C0DEED", "profile_sidebar_fill_color": "DDEEF6", "profile_text_color": "333333", "profile_use_background_image": true, "has_extended_profile": true, "default_profile": true, "default_profile_image": false, "following": false, "follow_request_sent": false, "notifications": false, "translator_type": "none"}, "geo": null, "coordinates": null, "place": {"id": "03b7ea94ef68e9d7", "url": "https://api.twitter.com/1.1/geo/id/03b7ea94ef68e9d7.json", "place_type": "city", "name": "Mylapore Tiruvallike", "full_name": "Mylapore Tiruvallike, India", "country_code": "IN", "country": "India", "contained_within": [], "bounding_box": {"type": "Polygon", "coordinates": [[[80.2348852, 12.970918], [80.288726, 12.970918], [80.288726, 13.0778711], [80.2348852, 13.0778711]]]}, "attributes": {}}, "contributors": null, "is_quote_status": false, "retweet_count": 2, "favorite_count": 6, "favorited": false, "retweeted": false, "possibly_sensitive": false, "lang": "en"}, "is_quote_status": false, "retweet_count": 2, "favorite_count": 0, "favorited": false, "retweeted": false, "lang": "en"}