{"created_at": "Wed Feb 27 13:21:22 +0000 2019", "id": 1100747721370230784, "id_str": "1100747721370230784", "full_text": "@HarshadDeshmu20 Look man, in war both side forces will die, both side will suffer huge losses, your current PM did the pulwama for his political campaign, your politicians are also raising the point, he is making you fool to win the election. Why BJP always call for war near ellection", "truncated": false, "display_text_range": [17, 286], "entities": {"hashtags": [], "symbols": [], "user_mentions": [{"screen_name": "HarshadDeshmu20", "name": "Harshad Deshmukh", "id": 737616716671287296, "id_str": "737616716671287296", "indices": [0, 16]}], "urls": []}, "metadata": {"iso_language_code": "en", "result_type": "recent"}, "source": "<a href=\"http://twitter.com/download/android\" rel=\"nofollow\">Twitter for Android</a>", "in_reply_to_status_id": 1100733528130625544, "in_reply_to_status_id_str": "1100733528130625544", "in_reply_to_user_id": 737616716671287296, "in_reply_to_user_id_str": "737616716671287296", "in_reply_to_screen_name": "HarshadDeshmu20", "user": {"id": 2162186272, "id_str": "2162186272", "name": "Zeeshan Gujjar", "screen_name": "Chukkayrakh", "location": "", "description": "", "url": null, "entities": {"description": {"urls": []}}, "protected": false, "followers_count": 129, "friends_count": 332, "listed_count": 0, "created_at": "Thu Oct 31 18:24:44 +0000 2013", "favourites_count": 6761, "utc_offset": null, "time_zone": null, "geo_enabled": true, "verified": false, "statuses_count": 4347, "lang": "en", "contributors_enabled": false, "is_translator": false, "is_translation_enabled": false, "profile_background_color": "C0DEED", "profile_background_image_url": "http://abs.twimg.com/images/themes/theme1/bg.png", "profile_background_image_url_https": "https://abs.twimg.com/images/themes/theme1/bg.png", "profile_background_tile": false, "profile_image_url": "http://pbs.twimg.com/profile_images/1100651164033581056/ac8aqJlA_normal.jpg", "profile_image_url_https": "https://pbs.twimg.com/profile_images/1100651164033581056/ac8aqJlA_normal.jpg", "profile_banner_url": "https://pbs.twimg.com/profile_banners/2162186272/1546343959", "profile_link_color": "1DA1F2", "profile_sidebar_border_color": "C0DEED", "profile_sidebar_fill_color": "DDEEF6", "profile_text_color": "333333", "profile_use_background_image": true, "has_extended_profile": true, "default_profile": true, "default_profile_image": false, "following": false, "follow_request_sent": false, "notifications": false, "translator_type": "none"}, "geo": null, "coordinates": null, "place": null, "contributors": null, "is_quote_status": false, "retweet_count": 0, "favorite_count": 0, "favorited": false, "retweeted": false, "lang": "en"}