{"created_at": "Wed Feb 27 12:35:22 +0000 2019", "id": 1100736145598615552, "id_str": "1100736145598615552", "full_text": "RT @whimsytulip: This! We simply can't afford BJP for another term. It would be disastrous. The Indian Air Force did a great job! Modi did\u2026", "truncated": false, "display_text_range": [0, 139], "entities": {"hashtags": [], "symbols": [], "user_mentions": [{"screen_name": "whimsytulip", "name": "Wanderlust", "id": 1038053612239314947, "id_str": "1038053612239314947", "indices": [3, 15]}], "urls": []}, "metadata": {"iso_language_code": "en", "result_type": "recent"}, "source": "<a href=\"http://twitter.com\" rel=\"nofollow\">Twitter Web Client</a>", "in_reply_to_status_id": null, "in_reply_to_status_id_str": null, "in_reply_to_user_id": null, "in_reply_to_user_id_str": null, "in_reply_to_screen_name": null, "user": {"id": 357416856, "id_str": "357416856", "name": "MadKing", "screen_name": "sanguru01", "location": "Perundurai", "description": "What is Dead may never Die.... !!!", "url": null, "entities": {"description": {"urls": []}}, "protected": false, "followers_count": 195, "friends_count": 159, "listed_count": 2, "created_at": "Thu Aug 18 10:06:19 +0000 2011", "favourites_count": 1585, "utc_offset": null, "time_zone": null, "geo_enabled": false, "verified": false, "statuses_count": 10199, "lang": "en", "contributors_enabled": false, "is_translator": false, "is_translation_enabled": false, "profile_background_color": "ABB8C2", "profile_background_image_url": "http://abs.twimg.com/images/themes/theme9/bg.gif", "profile_background_image_url_https": "https://abs.twimg.com/images/themes/theme9/bg.gif", "profile_background_tile": true, "profile_image_url": "http://pbs.twimg.com/profile_images/948783877677490177/gkZ14HlY_normal.jpg", "profile_image_url_https": "https://pbs.twimg.com/profile_images/948783877677490177/gkZ14HlY_normal.jpg", "profile_banner_url": "https://pbs.twimg.com/profile_banners/357416856/1437718770", "profile_link_color": "3B94D9", "profile_sidebar_border_color": "000000", "profile_sidebar_fill_color": "252429", "profile_text_color": "666666", "profile_use_background_image": true, "has_extended_profile": false, "default_profile": false, "default_profile_image": false, "following": false, "follow_request_sent": false, "notifications": false, "translator_type": "none"}, "geo": null, "coordinates": null, "place": null, "contributors": null, "retweeted_status": {"created_at": "Tue Feb 26 20:20:28 +0000 2019", "id": 1100490805989367808, "id_str": "1100490805989367808", "full_text": "This! We simply can't afford BJP for another term. It would be disastrous. The Indian Air Force did a great job! Modi did not. Its his cluelesness which led to all the pulwama,  pathankot in the first place.. https://t.co/Zs9GYi6Eig", "truncated": false, "display_text_range": [0, 208], "entities": {"hashtags": [], "symbols": [], "user_mentions": [], "urls": [{"url": "https://t.co/Zs9GYi6Eig", "expanded_url": "https://twitter.com/arattaigirl/status/1100381488082706432", "display_url": "twitter.com/arattaigirl/st\u2026", "indices": [209, 232]}]}, "metadata": {"iso_language_code": "en", "result_type": "recent"}, "source": "<a href=\"http://twitter.com/download/android\" rel=\"nofollow\">Twitter for Android</a>", "in_reply_to_status_id": null, "in_reply_to_status_id_str": null, "in_reply_to_user_id": null, "in_reply_to_user_id_str": null, "in_reply_to_screen_name": null, "user": {"id": 1038053612239314947, "id_str": "1038053612239314947", "name": "Wanderlust", "screen_name": "whimsytulip", "location": "", "description": "\u0ba8\u0bbe\u0ba9\u0bcd \u0ba8\u0bbe\u0bb2\u0bcd \u0baa\u0b95\u0bcd\u0b95\u0bae\u0bcd \u0ba8\u0bc0\u0bb0\u0bcd \u0b9a\u0bc2\u0bb4\u0bcd\u0ba8\u0bcd\u0ba4 \u0ba4\u0bc0\u0bb5\u0bb2\u0bcd\u0bb2\u0bb5\u0bbe..", "url": null, "entities": {"description": {"urls": []}}, "protected": false, "followers_count": 2485, "friends_count": 249, "listed_count": 7, "created_at": "Fri Sep 07 13:17:22 +0000 2018", "favourites_count": 77, "utc_offset": null, "time_zone": null, "geo_enabled": false, "verified": false, "statuses_count": 6270, "lang": "en", "contributors_enabled": false, "is_translator": false, "is_translation_enabled": false, "profile_background_color": "000000", "profile_background_image_url": "http://abs.twimg.com/images/themes/theme1/bg.png", "profile_background_image_url_https": "https://abs.twimg.com/images/themes/theme1/bg.png", "profile_background_tile": false, "profile_image_url": "http://pbs.twimg.com/profile_images/1076979148856254464/QbL9rKtO_normal.jpg", "profile_image_url_https": "https://pbs.twimg.com/profile_images/1076979148856254464/QbL9rKtO_normal.jpg", "profile_banner_url": "https://pbs.twimg.com/profile_banners/1038053612239314947/1536328560", "profile_link_color": "19CF86", "profile_sidebar_border_color": "000000", "profile_sidebar_fill_color": "000000", "profile_text_color": "000000", "profile_use_background_image": false, "has_extended_profile": false, "default_profile": false, "default_profile_image": false, "following": false, "follow_request_sent": false, "notifications": false, "translator_type": "none"}, "geo": null, "coordinates": null, "place": null, "contributors": null, "is_quote_status": true, "quoted_status_id": 1100381488082706432, "quoted_status_id_str": "1100381488082706432", "quoted_status": {"created_at": "Tue Feb 26 13:06:05 +0000 2019", "id": 1100381488082706432, "id_str": "1100381488082706432", "full_text": "\u0bae\u0bcb\u0b9f\u0bbf\u0b95\u0bcd\u0b95\u0bc1 \u0b93\u0b9f\u0bcd\u0b9f\u0bc1 \u0baa\u0bcb\u0b9f \u0bae\u0bbe\u0b9f\u0bcd\u0b9f\u0bc7\u0ba9\u0bcd\u0ba9\u0bc1 \u0b9a\u0bca\u0ba9\u0bcd\u0ba9\u0bbe \u0ba4\u0bc7\u0b9a\u0baa\u0b95\u0bcd\u0ba4\u0bbf \u0b87\u0bb2\u0bcd\u0bb2\u0bc8\u0baf\u0bbe\u0bae\u0bcd:) \u0bb0\u0bbe\u0ba3\u0bc1\u0bb5 \u0bb5\u0bc0\u0bb0\u0bb0\u0bcd\u0b95\u0bb3\u0bcb\u0b9f \u0b85\u0bb0\u0bcd\u0baa\u0bcd\u0baa\u0ba3\u0bbf\u0baa\u0bcd\u0baa\u0bc1\u0b95\u0bcd\u0b95\u0bc1\u0ba4\u0bcd\u0ba4\u0bbe\u0ba9\u0bcd \u0bae\u0bb0\u0bbf\u0baf\u0bbe\u0ba4\u0bc8. \u0b85\u0ba4\u0bc8 \u0b95\u0bbe\u0bb0\u0ba3\u0bae\u0bbe\u0b95\u0bcd\u0b95\u0bbf \u0bae\u0bcb\u0b9f\u0bbf\u0baf\u0bc8 \u0bb5\u0bc0\u0bb0\u0bb0\u0bbe\u0b95\u0bcd\u0b95 \u0ba4\u0bc7\u0bb5\u0bc8\u0baf\u0bbf\u0bb2\u0bcd\u0bb2\u0bc8.\u0baa\u0ba3\u0bae\u0ba4\u0bbf\u0baa\u0bcd\u0baa\u0bbf\u0bb4\u0baa\u0bcd\u0baa\u0bc1, \u0bae\u0ba4\u0bb5\u0bc6\u0bb1\u0bbf,\u0baa\u0b9a\u0bc1\u0bb5\u0bc1\u0b95\u0bcd\u0b95\u0bbe\u0b95 \u0bae\u0ba9\u0bc1\u0b9a\u0b99\u0bcd\u0b95\u0bb3\u0bc8 \u0b85\u0b9f\u0bbf\u0b9a\u0bcd\u0b9a\u0bc1\u0b95\u0bcd \u0b95\u0bca\u0ba9\u0bcd\u0ba9\u0ba4\u0bc1\u0ba9\u0bcd\u0ba9\u0bc1 \u0b8e\u0bb2\u0bcd\u0bb2\u0bbe\u0ba4\u0bcd\u0ba4\u0bc8\u0baf\u0bc1\u0bae\u0bcd \u0bae\u0bb1\u0ba8\u0bcd\u0ba4\u0bc1\u0b9f\u0bcd\u0b9f\u0bc1 \u0b93\u0b9f\u0bcd\u0b9f\u0bc1\u0baa\u0bcd \u0baa\u0bcb\u0b9f \u0bae\u0bc1\u0b9f\u0bbf\u0baf\u0bbe\u0ba4\u0bc1\u0ba9\u0bcd\u0bb1\u0ba4\u0bc1\u0ba4\u0bbe\u0ba9\u0bcd \u0ba8\u0bbf\u0bb2\u0bc8\u0baa\u0bcd\u0baa\u0bbe\u0b9f\u0bc1", "truncated": false, "display_text_range": [0, 279], "entities": {"hashtags": [], "symbols": [], "user_mentions": [], "urls": []}, "metadata": {"iso_language_code": "en", "result_type": "recent"}, "source": "<a href=\"http://twitter.com/download/android\" rel=\"nofollow\">Twitter for Android</a>", "in_reply_to_status_id": null, "in_reply_to_status_id_str": null, "in_reply_to_user_id": null, "in_reply_to_user_id_str": null, "in_reply_to_screen_name": null, "user": {"id": 287065145, "id_str": "287065145", "name": "\u0b9a\u0bcc\u0bae\u0bcd\u0baf\u0bbe :))", "screen_name": "arattaigirl", "location": "", "description": "", "url": "https://t.co/sDjAjMI7Nz", "entities": {"url": {"urls": [{"url": "https://t.co/sDjAjMI7Nz", "expanded_url": "http://www.arattaigirl.com", "display_url": "arattaigirl.com", "indices": [0, 23]}]}, "description": {"urls": []}}, "protected": false, "followers_count": 73867, "friends_count": 290, "listed_count": 226, "created_at": "Sun Apr 24 07:32:42 +0000 2011", "favourites_count": 4412, "utc_offset": null, "time_zone": null, "geo_enabled": false, "verified": false, "statuses_count": 81728, "lang": "en", "contributors_enabled": false, "is_translator": false, "is_translation_enabled": false, "profile_background_color": "131516", "profile_background_image_url": "http://abs.twimg.com/images/themes/theme14/bg.gif", "profile_background_image_url_https": "https://abs.twimg.com/images/themes/theme14/bg.gif", "profile_background_tile": true, "profile_image_url": "http://pbs.twimg.com/profile_images/1100388713308217344/Rj-eFIbC_normal.jpg", "profile_image_url_https": "https://pbs.twimg.com/profile_images/1100388713308217344/Rj-eFIbC_normal.jpg", "profile_banner_url": "https://pbs.twimg.com/profile_banners/287065145/1547433482", "profile_link_color": "009999", "profile_sidebar_border_color": "EEEEEE", "profile_sidebar_fill_color": "EFEFEF", "profile_text_color": "333333", "profile_use_background_image": true, "has_extended_profile": false, "default_profile": false, "default_profile_image": false, "following": false, "follow_request_sent": false, "notifications": false, "translator_type": "none"}, "geo": null, "coordinates": null, "place": null, "contributors": null, "is_quote_status": false, "retweet_count": 472, "favorite_count": 769, "favorited": false, "retweeted": false, "lang": "ta"}, "retweet_count": 6, "favorite_count": 12, "favorited": false, "retweeted": false, "possibly_sensitive": false, "lang": "en"}, "is_quote_status": true, "quoted_status_id": 1100381488082706432, "quoted_status_id_str": "1100381488082706432", "retweet_count": 6, "favorite_count": 0, "favorited": false, "retweeted": false, "lang": "en"}