{"created_at": "Wed Feb 27 13:12:17 +0000 2019", "id": 1100745434878767104, "id_str": "1100745434878767104", "full_text": "Do we really need elections? Can\u2019t just Narendra Modi continue his term as it is as the Prime Minister for the next 5 years? @narendramodi @PMOIndia @BJP4India", "truncated": false, "display_text_range": [0, 159], "entities": {"hashtags": [], "symbols": [], "user_mentions": [{"screen_name": "narendramodi", "name": "Narendra Modi", "id": 18839785, "id_str": "18839785", "indices": [125, 138]}, {"screen_name": "PMOIndia", "name": "PMO India", "id": 471741741, "id_str": "471741741", "indices": [139, 148]}, {"screen_name": "BJP4India", "name": "BJP", "id": 207809313, "id_str": "207809313", "indices": [149, 159]}], "urls": []}, "metadata": {"iso_language_code": "en", "result_type": "recent"}, "source": "<a href=\"http://twitter.com/download/iphone\" rel=\"nofollow\">Twitter for iPhone</a>", "in_reply_to_status_id": null, "in_reply_to_status_id_str": null, "in_reply_to_user_id": null, "in_reply_to_user_id_str": null, "in_reply_to_screen_name": null, "user": {"id": 124772723, "id_str": "124772723", "name": "Nilesh Sawant", "screen_name": "sawnilrules", "location": "Mumbai", "description": "Reviewer| Entrepreneur| Work to Live| Live to Drive| Founder- Motorise Inc", "url": "https://t.co/5QySliyWrh", "entities": {"url": {"urls": [{"url": "https://t.co/5QySliyWrh", "expanded_url": "http://www.motorise.in", "display_url": "motorise.in", "indices": [0, 23]}]}, "description": {"urls": []}}, "protected": false, "followers_count": 59, "friends_count": 109, "listed_count": 2, "created_at": "Sat Mar 20 14:22:27 +0000 2010", "favourites_count": 45, "utc_offset": null, "time_zone": null, "geo_enabled": false, "verified": false, "statuses_count": 560, "lang": "en", "contributors_enabled": false, "is_translator": false, "is_translation_enabled": false, "profile_background_color": "C0DEED", "profile_background_image_url": "http://abs.twimg.com/images/themes/theme1/bg.png", "profile_background_image_url_https": "https://abs.twimg.com/images/themes/theme1/bg.png", "profile_background_tile": false, "profile_image_url": "http://pbs.twimg.com/profile_images/1100578846003347461/-M679V0G_normal.jpg", "profile_image_url_https": "https://pbs.twimg.com/profile_images/1100578846003347461/-M679V0G_normal.jpg", "profile_banner_url": "https://pbs.twimg.com/profile_banners/124772723/1550629237", "profile_link_color": "1DA1F2", "profile_sidebar_border_color": "C0DEED", "profile_sidebar_fill_color": "DDEEF6", "profile_text_color": "333333", "profile_use_background_image": true, "has_extended_profile": true, "default_profile": true, "default_profile_image": false, "following": false, "follow_request_sent": false, "notifications": false, "translator_type": "none"}, "geo": null, "coordinates": null, "place": null, "contributors": null, "is_quote_status": false, "retweet_count": 0, "favorite_count": 0, "favorited": false, "retweeted": false, "lang": "en"}