{"created_at": "Wed Feb 27 13:30:07 +0000 2019", "id": 1100749923505590274, "id_str": "1100749923505590274", "full_text": "RT @scroll_in: #LIVE | Former J&amp;K Chief Minister Omar Abdullah says Prime Minister Narendra Modi must suspend his political activities unti\u2026", "truncated": false, "display_text_range": [0, 144], "entities": {"hashtags": [{"text": "LIVE", "indices": [15, 20]}], "symbols": [], "user_mentions": [{"screen_name": "scroll_in", "name": "scroll.in", "id": 414946220, "id_str": "414946220", "indices": [3, 13]}], "urls": []}, "metadata": {"iso_language_code": "en", "result_type": "recent"}, "source": "<a href=\"http://twitter.com\" rel=\"nofollow\">Twitter Web Client</a>", "in_reply_to_status_id": null, "in_reply_to_status_id_str": null, "in_reply_to_user_id": null, "in_reply_to_user_id_str": null, "in_reply_to_screen_name": null, "user": {"id": 296688992, "id_str": "296688992", "name": "Mukesh \u0645\u06a9\u06cc\u0634 \u062c\u0648\u0646", "screen_name": "mukeshjune", "location": "India", "description": "\u201cThe connections we make in the course of a life\u2013maybe that\u2019s what heaven is.\u201d\n\u2015Fred Rogers", "url": null, "entities": {"description": {"urls": []}}, "protected": false, "followers_count": 1020, "friends_count": 909, "listed_count": 18, "created_at": "Wed May 11 07:15:40 +0000 2011", "favourites_count": 127205, "utc_offset": null, "time_zone": null, "geo_enabled": false, "verified": false, "statuses_count": 67514, "lang": "en", "contributors_enabled": false, "is_translator": false, "is_translation_enabled": false, "profile_background_color": "DADDC0", "profile_background_image_url": "http://abs.twimg.com/images/themes/theme1/bg.png", "profile_background_image_url_https": "https://abs.twimg.com/images/themes/theme1/bg.png", "profile_background_tile": true, "profile_image_url": "http://pbs.twimg.com/profile_images/1093513319682576390/_SCJrZXT_normal.jpg", "profile_image_url_https": "https://pbs.twimg.com/profile_images/1093513319682576390/_SCJrZXT_normal.jpg", "profile_banner_url": "https://pbs.twimg.com/profile_banners/296688992/1548678379", "profile_link_color": "6C961C", "profile_sidebar_border_color": "FFFFFF", "profile_sidebar_fill_color": "E2EAEF", "profile_text_color": "877F63", "profile_use_background_image": true, "has_extended_profile": false, "default_profile": false, "default_profile_image": false, "following": false, "follow_request_sent": false, "notifications": false, "translator_type": "none"}, "geo": null, "coordinates": null, "place": null, "contributors": null, "retweeted_status": {"created_at": "Wed Feb 27 12:53:16 +0000 2019", "id": 1100740648599203841, "id_str": "1100740648599203841", "full_text": "#LIVE | Former J&amp;K Chief Minister Omar Abdullah says Prime Minister Narendra Modi must suspend his political activities until missing Wing Commander #Abhinandan is returned safely. https://t.co/FG2hcpGY3X https://t.co/jVo6Ft2Ybw", "truncated": false, "display_text_range": [0, 208], "entities": {"hashtags": [{"text": "LIVE", "indices": [0, 5]}, {"text": "Abhinandan", "indices": [153, 164]}], "symbols": [], "user_mentions": [], "urls": [{"url": "https://t.co/FG2hcpGY3X", "expanded_url": "https://scroll.in/latest/914747/iaf-air-strikes-sushma-swaraj-meets-chinese-foreign-minister-raises-pulwama-attack", "display_url": "scroll.in/latest/914747/\u2026", "indices": [185, 208]}], "media": [{"id": 1100740459977154560, "id_str": "1100740459977154560", "indices": [209, 232], "media_url": "http://pbs.twimg.com/media/D0adncrWoAAl6gp.jpg", "media_url_https": "https://pbs.twimg.com/media/D0adncrWoAAl6gp.jpg", "url": "https://t.co/jVo6Ft2Ybw", "display_url": "pic.twitter.com/jVo6Ft2Ybw", "expanded_url": "https://twitter.com/scroll_in/status/1100740648599203841/photo/1", "type": "photo", "sizes": {"thumb": {"w": 150, "h": 150, "resize": "crop"}, "large": {"w": 1200, "h": 799, "resize": "fit"}, "small": {"w": 680, "h": 453, "resize": "fit"}, "medium": {"w": 1200, "h": 799, "resize": "fit"}}}]}, "extended_entities": {"media": [{"id": 1100740459977154560, "id_str": "1100740459977154560", "indices": [209, 232], "media_url": "http://pbs.twimg.com/media/D0adncrWoAAl6gp.jpg", "media_url_https": "https://pbs.twimg.com/media/D0adncrWoAAl6gp.jpg", "url": "https://t.co/jVo6Ft2Ybw", "display_url": "pic.twitter.com/jVo6Ft2Ybw", "expanded_url": "https://twitter.com/scroll_in/status/1100740648599203841/photo/1", "type": "photo", "sizes": {"thumb": {"w": 150, "h": 150, "resize": "crop"}, "large": {"w": 1200, "h": 799, "resize": "fit"}, "small": {"w": 680, "h": 453, "resize": "fit"}, "medium": {"w": 1200, "h": 799, "resize": "fit"}}}]}, "metadata": {"iso_language_code": "en", "result_type": "recent"}, "source": "<a href=\"http://twitter.com\" rel=\"nofollow\">Twitter Web Client</a>", "in_reply_to_status_id": 1100729891216076805, "in_reply_to_status_id_str": "1100729891216076805", "in_reply_to_user_id": 414946220, "in_reply_to_user_id_str": "414946220", "in_reply_to_screen_name": "scroll_in", "user": {"id": 414946220, "id_str": "414946220", "name": "scroll.in", "screen_name": "scroll_in", "location": "", "description": "India's leading independent source of news, analysis and culture.", "url": "http://t.co/XqwnvGmcxx", "entities": {"url": {"urls": [{"url": "http://t.co/XqwnvGmcxx", "expanded_url": "http://scroll.in", "display_url": "scroll.in", "indices": [0, 22]}]}, "description": {"urls": []}}, "protected": false, "followers_count": 218947, "friends_count": 81, "listed_count": 1332, "created_at": "Thu Nov 17 18:03:25 +0000 2011", "favourites_count": 158, "utc_offset": null, "time_zone": null, "geo_enabled": true, "verified": true, "statuses_count": 226451, "lang": "en", "contributors_enabled": false, "is_translator": false, "is_translation_enabled": false, "profile_background_color": "000000", "profile_background_image_url": "http://abs.twimg.com/images/themes/theme1/bg.png", "profile_background_image_url_https": "https://abs.twimg.com/images/themes/theme1/bg.png", "profile_background_tile": false, "profile_image_url": "http://pbs.twimg.com/profile_images/1038263519811174400/2LoEmb49_normal.jpg", "profile_image_url_https": "https://pbs.twimg.com/profile_images/1038263519811174400/2LoEmb49_normal.jpg", "profile_banner_url": "https://pbs.twimg.com/profile_banners/414946220/1548334798", "profile_link_color": "FA743E", "profile_sidebar_border_color": "000000", "profile_sidebar_fill_color": "000000", "profile_text_color": "000000", "profile_use_background_image": false, "has_extended_profile": false, "default_profile": false, "default_profile_image": false, "following": false, "follow_request_sent": false, "notifications": false, "translator_type": "none"}, "geo": null, "coordinates": null, "place": null, "contributors": null, "is_quote_status": false, "retweet_count": 6, "favorite_count": 18, "favorited": false, "retweeted": false, "possibly_sensitive": false, "lang": "en"}, "is_quote_status": false, "retweet_count": 6, "favorite_count": 0, "favorited": false, "retweeted": false, "lang": "en"}