{"created_at": "Wed Feb 27 15:13:37 +0000 2019", "id": 1100775972545224704, "id_str": "1100775972545224704", "full_text": "Prime Minister Narendra Modi has been nominated for Nobel Peace Prize 2019 for launching the world\u2019s largest healthcare scheme\n#SayNoToWar", "truncated": false, "display_text_range": [0, 138], "entities": {"hashtags": [{"text": "SayNoToWar", "indices": [127, 138]}], "symbols": [], "user_mentions": [], "urls": []}, "metadata": {"iso_language_code": "en", "result_type": "recent"}, "source": "<a href=\"http://twitter.com/download/android\" rel=\"nofollow\">Twitter for Android</a>", "in_reply_to_status_id": null, "in_reply_to_status_id_str": null, "in_reply_to_user_id": null, "in_reply_to_user_id_str": null, "in_reply_to_screen_name": null, "user": {"id": 1306999357, "id_str": "1306999357", "name": "Dr.Uzma", "screen_name": "officialdruzma", "location": "Islamabad, Pakistan", "description": "MNA Candidate, Political Party Dev. Trainer, Policy Maker, Strategic Consultant, Human Rights and Peace Activist, Young Women Ambassador of Pakistan", "url": "https://t.co/ErKHgqrYe1", "entities": {"url": {"urls": [{"url": "https://t.co/ErKHgqrYe1", "expanded_url": "http://about.me/dr.uzma", "display_url": "about.me/dr.uzma", "indices": [0, 23]}]}, "description": {"urls": []}}, "protected": false, "followers_count": 3610, "friends_count": 3850, "listed_count": 14, "created_at": "Wed Mar 27 09:17:15 +0000 2013", "favourites_count": 5010, "utc_offset": null, "time_zone": null, "geo_enabled": true, "verified": false, "statuses_count": 4252, "lang": "en", "contributors_enabled": false, "is_translator": false, "is_translation_enabled": false, "profile_background_color": "EBEBEB", "profile_background_image_url": "http://abs.twimg.com/images/themes/theme7/bg.gif", "profile_background_image_url_https": "https://abs.twimg.com/images/themes/theme7/bg.gif", "profile_background_tile": false, "profile_image_url": "http://pbs.twimg.com/profile_images/989040773113970689/sNBa1Qcd_normal.jpg", "profile_image_url_https": "https://pbs.twimg.com/profile_images/989040773113970689/sNBa1Qcd_normal.jpg", "profile_banner_url": "https://pbs.twimg.com/profile_banners/1306999357/1484931111", "profile_link_color": "990000", "profile_sidebar_border_color": "DFDFDF", "profile_sidebar_fill_color": "F3F3F3", "profile_text_color": "333333", "profile_use_background_image": true, "has_extended_profile": true, "default_profile": false, "default_profile_image": false, "following": false, "follow_request_sent": false, "notifications": false, "translator_type": "none"}, "geo": null, "coordinates": null, "place": null, "contributors": null, "is_quote_status": false, "retweet_count": 0, "favorite_count": 2, "favorited": false, "retweeted": false, "lang": "en"}