{"created_at": "Wed Feb 27 15:22:39 +0000 2019", "id": 1100778243349598208, "id_str": "1100778243349598208", "full_text": "RT @arunjaitley: Prime Minister Narendra Modi\u2019s reply in Parliament is a Report Card of the Government\u2019s Five Year Performance. @narendramo\u2026", "truncated": false, "display_text_range": [0, 140], "entities": {"hashtags": [], "symbols": [], "user_mentions": [{"screen_name": "arunjaitley", "name": "Arun Jaitley", "id": 2183816041, "id_str": "2183816041", "indices": [3, 15]}], "urls": []}, "metadata": {"iso_language_code": "en", "result_type": "recent"}, "source": "<a href=\"http://twitter.com\" rel=\"nofollow\">Twitter Web Client</a>", "in_reply_to_status_id": null, "in_reply_to_status_id_str": null, "in_reply_to_user_id": null, "in_reply_to_user_id_str": null, "in_reply_to_screen_name": null, "user": {"id": 1096353298666254336, "id_str": "1096353298666254336", "name": "karan", "screen_name": "karan89419345", "location": "Bhopal, India", "description": "i am hard worker", "url": null, "entities": {"description": {"urls": []}}, "protected": false, "followers_count": 14, "friends_count": 22, "listed_count": 0, "created_at": "Fri Feb 15 10:19:30 +0000 2019", "favourites_count": 6391, "utc_offset": null, "time_zone": null, "geo_enabled": false, "verified": false, "statuses_count": 2642, "lang": "en", "contributors_enabled": false, "is_translator": false, "is_translation_enabled": false, "profile_background_color": "F5F8FA", "profile_background_image_url": null, "profile_background_image_url_https": null, "profile_background_tile": false, "profile_image_url": "http://pbs.twimg.com/profile_images/1096474548982009856/nfMAlGJ0_normal.jpg", "profile_image_url_https": "https://pbs.twimg.com/profile_images/1096474548982009856/nfMAlGJ0_normal.jpg", "profile_link_color": "1DA1F2", "profile_sidebar_border_color": "C0DEED", "profile_sidebar_fill_color": "DDEEF6", "profile_text_color": "333333", "profile_use_background_image": true, "has_extended_profile": true, "default_profile": true, "default_profile_image": false, "following": false, "follow_request_sent": false, "notifications": false, "translator_type": "none"}, "geo": null, "coordinates": null, "place": null, "contributors": null, "retweeted_status": {"created_at": "Thu Feb 07 14:49:53 +0000 2019", "id": 1093522240409423874, "id_str": "1093522240409423874", "full_text": "Prime Minister Narendra Modi\u2019s reply in Parliament is a Report Card of the Government\u2019s Five Year Performance. @narendramodi", "truncated": false, "display_text_range": [0, 124], "entities": {"hashtags": [], "symbols": [], "user_mentions": [{"screen_name": "narendramodi", "name": "Narendra Modi", "id": 18839785, "id_str": "18839785", "indices": [111, 124]}], "urls": []}, "metadata": {"iso_language_code": "en", "result_type": "recent"}, "source": "<a href=\"http://twitter.com/download/iphone\" rel=\"nofollow\">Twitter for iPhone</a>", "in_reply_to_status_id": null, "in_reply_to_status_id_str": null, "in_reply_to_user_id": null, "in_reply_to_user_id_str": null, "in_reply_to_screen_name": null, "user": {"id": 2183816041, "id_str": "2183816041", "name": "Arun Jaitley", "screen_name": "arunjaitley", "location": "New Delhi", "description": "Minister of Finance and Corporate Affairs, Government of India", "url": "https://t.co/IkrHmWuct3", "entities": {"url": {"urls": [{"url": "https://t.co/IkrHmWuct3", "expanded_url": "http://on.fb.me/Ohlwz0", "display_url": "on.fb.me/Ohlwz0", "indices": [0, 23]}]}, "description": {"urls": []}}, "protected": false, "followers_count": 14126877, "friends_count": 160, "listed_count": 3194, "created_at": "Sat Nov 09 07:33:10 +0000 2013", "favourites_count": 38, "utc_offset": null, "time_zone": null, "geo_enabled": false, "verified": true, "statuses_count": 3318, "lang": "en", "contributors_enabled": false, "is_translator": false, "is_translation_enabled": false, "profile_background_color": "BF5B0D", "profile_background_image_url": "http://abs.twimg.com/images/themes/theme1/bg.png", "profile_background_image_url_https": "https://abs.twimg.com/images/themes/theme1/bg.png", "profile_background_tile": false, "profile_image_url": "http://pbs.twimg.com/profile_images/378800000828197225/f1d53aeab8f0534c7d73b0fbd5651130_normal.png", "profile_image_url_https": "https://pbs.twimg.com/profile_images/378800000828197225/f1d53aeab8f0534c7d73b0fbd5651130_normal.png", "profile_banner_url": "https://pbs.twimg.com/profile_banners/2183816041/1479566181", "profile_link_color": "0084B4", "profile_sidebar_border_color": "FFFFFF", "profile_sidebar_fill_color": "DDEEF6", "profile_text_color": "333333", "profile_use_background_image": true, "has_extended_profile": true, "default_profile": false, "default_profile_image": false, "following": true, "follow_request_sent": false, "notifications": false, "translator_type": "none"}, "geo": null, "coordinates": null, "place": null, "contributors": null, "is_quote_status": false, "retweet_count": 2626, "favorite_count": 13361, "favorited": false, "retweeted": false, "lang": "en"}, "is_quote_status": false, "retweet_count": 2626, "favorite_count": 0, "favorited": false, "retweeted": false, "lang": "en"}