{"created_at": "Wed Feb 27 18:11:11 +0000 2019", "id": 1100820655576993792, "id_str": "1100820655576993792", "full_text": "If they dont end war,then war will end them! Isn\u2019nt it Mr.Narendra Modi &amp; Mr.Imran Khan? &amp; what the terror funding or terror groups will do!They will find another soil.India &amp; Pakistan can rule the Asian world if they work combined #India #Pakistan @narendramodi @ImranKhanPTI https://t.co/uWLNVlppAL", "truncated": false, "display_text_range": [0, 288], "entities": {"hashtags": [{"text": "India", "indices": [244, 250]}, {"text": "Pakistan", "indices": [251, 260]}], "symbols": [], "user_mentions": [{"screen_name": "narendramodi", "name": "Narendra Modi", "id": 18839785, "id_str": "18839785", "indices": [261, 274]}, {"screen_name": "ImranKhanPTI", "name": "Imran Khan", "id": 122453931, "id_str": "122453931", "indices": [275, 288]}], "urls": [], "media": [{"id": 1100820641928736768, "id_str": "1100820641928736768", "indices": [289, 312], "media_url": "http://pbs.twimg.com/media/D0bmipuUcAAHiLY.jpg", "media_url_https": "https://pbs.twimg.com/media/D0bmipuUcAAHiLY.jpg", "url": "https://t.co/uWLNVlppAL", "display_url": "pic.twitter.com/uWLNVlppAL", "expanded_url": "https://twitter.com/asianewsteam/status/1100820655576993792/photo/1", "type": "photo", "sizes": {"thumb": {"w": 150, "h": 150, "resize": "crop"}, "large": {"w": 840, "h": 477, "resize": "fit"}, "medium": {"w": 840, "h": 477, "resize": "fit"}, "small": {"w": 680, "h": 386, "resize": "fit"}}}]}, "extended_entities": {"media": [{"id": 1100820641928736768, "id_str": "1100820641928736768", "indices": [289, 312], "media_url": "http://pbs.twimg.com/media/D0bmipuUcAAHiLY.jpg", "media_url_https": "https://pbs.twimg.com/media/D0bmipuUcAAHiLY.jpg", "url": "https://t.co/uWLNVlppAL", "display_url": "pic.twitter.com/uWLNVlppAL", "expanded_url": "https://twitter.com/asianewsteam/status/1100820655576993792/photo/1", "type": "photo", "sizes": {"thumb": {"w": 150, "h": 150, "resize": "crop"}, "large": {"w": 840, "h": 477, "resize": "fit"}, "medium": {"w": 840, "h": 477, "resize": "fit"}, "small": {"w": 680, "h": 386, "resize": "fit"}}}]}, "metadata": {"iso_language_code": "en", "result_type": "recent"}, "source": "<a href=\"http://twitter.com/download/iphone\" rel=\"nofollow\">Twitter for iPhone</a>", "in_reply_to_status_id": null, "in_reply_to_status_id_str": null, "in_reply_to_user_id": null, "in_reply_to_user_id_str": null, "in_reply_to_screen_name": null, "user": {"id": 992069133687840768, "id_str": "992069133687840768", "name": "Asia News", "screen_name": "asianewsteam", "location": "Bangkok, Thailand", "description": "Asia News is an online News platform that brings Asia to the global online audience. follow us for fastest news updates - https://t.co/D57LLgG475", "url": "https://t.co/jNd49UIsSd", "entities": {"url": {"urls": [{"url": "https://t.co/jNd49UIsSd", "expanded_url": "http://www.asianews.press", "display_url": "asianews.press", "indices": [0, 23]}]}, "description": {"urls": [{"url": "https://t.co/D57LLgG475", "expanded_url": "http://facebook.com/asianewsteam", "display_url": "facebook.com/asianewsteam", "indices": [122, 145]}]}}, "protected": false, "followers_count": 2512, "friends_count": 1647, "listed_count": 2, "created_at": "Thu May 03 15:51:28 +0000 2018", "favourites_count": 7125, "utc_offset": null, "time_zone": null, "geo_enabled": true, "verified": false, "statuses_count": 11262, "lang": "en", "contributors_enabled": false, "is_translator": false, "is_translation_enabled": false, "profile_background_color": "F5F8FA", "profile_background_image_url": null, "profile_background_image_url_https": null, "profile_background_tile": false, "profile_image_url": "http://pbs.twimg.com/profile_images/1081529419267694594/KMFYBfTm_normal.jpg", "profile_image_url_https": "https://pbs.twimg.com/profile_images/1081529419267694594/KMFYBfTm_normal.jpg", "profile_banner_url": "https://pbs.twimg.com/profile_banners/992069133687840768/1546691663", "profile_link_color": "1DA1F2", "profile_sidebar_border_color": "C0DEED", "profile_sidebar_fill_color": "DDEEF6", "profile_text_color": "333333", "profile_use_background_image": true, "has_extended_profile": false, "default_profile": true, "default_profile_image": false, "following": false, "follow_request_sent": false, "notifications": false, "translator_type": "none"}, "geo": null, "coordinates": null, "place": null, "contributors": null, "is_quote_status": false, "retweet_count": 0, "favorite_count": 0, "favorited": false, "retweeted": false, "possibly_sensitive": false, "lang": "en"}