{"created_at": "Wed Feb 27 16:52:14 +0000 2019", "id": 1100800788304023552, "id_str": "1100800788304023552", "full_text": "RT @LoyalSachinFan: Imrand khan : We'll retaliate \n\nNarendra Modi ji : \n\n#SurgicalStrike2  #IndianAirForce https://t.co/ccde1cMPSl", "truncated": false, "display_text_range": [0, 130], "entities": {"hashtags": [{"text": "SurgicalStrike2", "indices": [73, 89]}, {"text": "IndianAirForce", "indices": [91, 106]}], "symbols": [], "user_mentions": [{"screen_name": "LoyalSachinFan", "name": "R A T N I $ H", "id": 292300972, "id_str": "292300972", "indices": [3, 18]}], "urls": [], "media": [{"id": 1100335442296225798, "id_str": "1100335442296225798", "indices": [107, 130], "media_url": "http://pbs.twimg.com/media/D0UtQUPWwAYLIey.jpg", "media_url_https": "https://pbs.twimg.com/media/D0UtQUPWwAYLIey.jpg", "url": "https://t.co/ccde1cMPSl", "display_url": "pic.twitter.com/ccde1cMPSl", "expanded_url": "https://twitter.com/LoyalSachinFan/status/1100335458318471168/photo/1", "type": "photo", "sizes": {"large": {"w": 765, "h": 401, "resize": "fit"}, "thumb": {"w": 150, "h": 150, "resize": "crop"}, "medium": {"w": 765, "h": 401, "resize": "fit"}, "small": {"w": 680, "h": 356, "resize": "fit"}}, "source_status_id": 1100335458318471168, "source_status_id_str": "1100335458318471168", "source_user_id": 292300972, "source_user_id_str": "292300972"}]}, "extended_entities": {"media": [{"id": 1100335442296225798, "id_str": "1100335442296225798", "indices": [107, 130], "media_url": "http://pbs.twimg.com/media/D0UtQUPWwAYLIey.jpg", "media_url_https": "https://pbs.twimg.com/media/D0UtQUPWwAYLIey.jpg", "url": "https://t.co/ccde1cMPSl", "display_url": "pic.twitter.com/ccde1cMPSl", "expanded_url": "https://twitter.com/LoyalSachinFan/status/1100335458318471168/photo/1", "type": "photo", "sizes": {"large": {"w": 765, "h": 401, "resize": "fit"}, "thumb": {"w": 150, "h": 150, "resize": "crop"}, "medium": {"w": 765, "h": 401, "resize": "fit"}, "small": {"w": 680, "h": 356, "resize": "fit"}}, "source_status_id": 1100335458318471168, "source_status_id_str": "1100335458318471168", "source_user_id": 292300972, "source_user_id_str": "292300972"}]}, "metadata": {"iso_language_code": "en", "result_type": "recent"}, "source": "<a href=\"https://mobile.twitter.com\" rel=\"nofollow\">Twitter Web App</a>", "in_reply_to_status_id": null, "in_reply_to_status_id_str": null, "in_reply_to_user_id": null, "in_reply_to_user_id_str": null, "in_reply_to_screen_name": null, "user": {"id": 901011853916217344, "id_str": "901011853916217344", "name": "Amarjeet Singh", "screen_name": "iAmarsingh9", "location": "New Delhi, India", "description": "Sabka Kalyan Ho", "url": null, "entities": {"description": {"urls": []}}, "protected": false, "followers_count": 511, "friends_count": 212, "listed_count": 0, "created_at": "Fri Aug 25 09:22:20 +0000 2017", "favourites_count": 11997, "utc_offset": null, "time_zone": null, "geo_enabled": false, "verified": false, "statuses_count": 12330, "lang": "en", "contributors_enabled": false, "is_translator": false, "is_translation_enabled": false, "profile_background_color": "F5F8FA", "profile_background_image_url": null, "profile_background_image_url_https": null, "profile_background_tile": false, "profile_image_url": "http://pbs.twimg.com/profile_images/1093756792402776064/XxIk2XMw_normal.jpg", "profile_image_url_https": "https://pbs.twimg.com/profile_images/1093756792402776064/XxIk2XMw_normal.jpg", "profile_banner_url": "https://pbs.twimg.com/profile_banners/901011853916217344/1505383514", "profile_link_color": "1DA1F2", "profile_sidebar_border_color": "C0DEED", "profile_sidebar_fill_color": "DDEEF6", "profile_text_color": "333333", "profile_use_background_image": true, "has_extended_profile": true, "default_profile": true, "default_profile_image": false, "following": false, "follow_request_sent": false, "notifications": false, "translator_type": "none"}, "geo": null, "coordinates": null, "place": null, "contributors": null, "retweeted_status": {"created_at": "Tue Feb 26 10:03:11 +0000 2019", "id": 1100335458318471168, "id_str": "1100335458318471168", "full_text": "Imrand khan : We'll retaliate \n\nNarendra Modi ji : \n\n#SurgicalStrike2  #IndianAirForce https://t.co/ccde1cMPSl", "truncated": false, "display_text_range": [0, 86], "entities": {"hashtags": [{"text": "SurgicalStrike2", "indices": [53, 69]}, {"text": "IndianAirForce", "indices": [71, 86]}], "symbols": [], "user_mentions": [], "urls": [], "media": [{"id": 1100335442296225798, "id_str": "1100335442296225798", "indices": [87, 110], "media_url": "http://pbs.twimg.com/media/D0UtQUPWwAYLIey.jpg", "media_url_https": "https://pbs.twimg.com/media/D0UtQUPWwAYLIey.jpg", "url": "https://t.co/ccde1cMPSl", "display_url": "pic.twitter.com/ccde1cMPSl", "expanded_url": "https://twitter.com/LoyalSachinFan/status/1100335458318471168/photo/1", "type": "photo", "sizes": {"large": {"w": 765, "h": 401, "resize": "fit"}, "thumb": {"w": 150, "h": 150, "resize": "crop"}, "medium": {"w": 765, "h": 401, "resize": "fit"}, "small": {"w": 680, "h": 356, "resize": "fit"}}}]}, "extended_entities": {"media": [{"id": 1100335442296225798, "id_str": "1100335442296225798", "indices": [87, 110], "media_url": "http://pbs.twimg.com/media/D0UtQUPWwAYLIey.jpg", "media_url_https": "https://pbs.twimg.com/media/D0UtQUPWwAYLIey.jpg", "url": "https://t.co/ccde1cMPSl", "display_url": "pic.twitter.com/ccde1cMPSl", "expanded_url": "https://twitter.com/LoyalSachinFan/status/1100335458318471168/photo/1", "type": "photo", "sizes": {"large": {"w": 765, "h": 401, "resize": "fit"}, "thumb": {"w": 150, "h": 150, "resize": "crop"}, "medium": {"w": 765, "h": 401, "resize": "fit"}, "small": {"w": 680, "h": 356, "resize": "fit"}}}]}, "metadata": {"iso_language_code": "en", "result_type": "recent"}, "source": "<a href=\"http://twitter.com/download/iphone\" rel=\"nofollow\">Twitter for iPhone</a>", "in_reply_to_status_id": null, "in_reply_to_status_id_str": null, "in_reply_to_user_id": null, "in_reply_to_user_id_str": null, "in_reply_to_screen_name": null, "user": {"id": 292300972, "id_str": "292300972", "name": "R A T N I $ H", "screen_name": "LoyalSachinFan", "location": "Jaha Koi Aata Jata Nahi ", "description": "Life's Become Boring After SACHIN's Retirement!! Looking For a restart button in life! MUMBAI INDIANS fan for life\ud83d\udc99", "url": null, "entities": {"description": {"urls": []}}, "protected": false, "followers_count": 5656, "friends_count": 664, "listed_count": 11, "created_at": "Tue May 03 12:42:49 +0000 2011", "favourites_count": 24803, "utc_offset": null, "time_zone": null, "geo_enabled": true, "verified": false, "statuses_count": 52692, "lang": "en", "contributors_enabled": false, "is_translator": false, "is_translation_enabled": false, "profile_background_color": "C0DEED", "profile_background_image_url": "http://abs.twimg.com/images/themes/theme1/bg.png", "profile_background_image_url_https": "https://abs.twimg.com/images/themes/theme1/bg.png", "profile_background_tile": false, "profile_image_url": "http://pbs.twimg.com/profile_images/1100306649040990208/BN9Wm6Ke_normal.jpg", "profile_image_url_https": "https://pbs.twimg.com/profile_images/1100306649040990208/BN9Wm6Ke_normal.jpg", "profile_banner_url": "https://pbs.twimg.com/profile_banners/292300972/1456633101", "profile_link_color": "1DA1F2", "profile_sidebar_border_color": "C0DEED", "profile_sidebar_fill_color": "DDEEF6", "profile_text_color": "333333", "profile_use_background_image": true, "has_extended_profile": true, "default_profile": true, "default_profile_image": false, "following": false, "follow_request_sent": false, "notifications": false, "translator_type": "none"}, "geo": null, "coordinates": null, "place": null, "contributors": null, "is_quote_status": false, "retweet_count": 160, "favorite_count": 669, "favorited": false, "retweeted": false, "possibly_sensitive": false, "lang": "en"}, "is_quote_status": false, "retweet_count": 160, "favorite_count": 0, "favorited": false, "retweeted": false, "possibly_sensitive": false, "lang": "en"}