{"created_at": "Wed Feb 27 12:40:39 +0000 2019", "id": 1100737473544708096, "id_str": "1100737473544708096", "full_text": "Narendra Modi must use Balakot to consolidate India\u2019s rajasic transformation https://t.co/wTe9DnRqwQ via @orfonline", "truncated": false, "display_text_range": [0, 115], "entities": {"hashtags": [], "symbols": [], "user_mentions": [{"screen_name": "orfonline", "name": "ORF", "id": 180748385, "id_str": "180748385", "indices": [105, 115]}], "urls": [{"url": "https://t.co/wTe9DnRqwQ", "expanded_url": "https://www.orfonline.org/expert-speak/narendra-modi-must-use-balakot-to-consolidate-indias-rajasic-transformation-48607/", "display_url": "orfonline.org/expert-speak/n\u2026", "indices": [77, 100]}]}, "metadata": {"iso_language_code": "en", "result_type": "recent"}, "source": "<a href=\"http://twitter.com/download/android\" rel=\"nofollow\">Twitter for Android</a>", "in_reply_to_status_id": null, "in_reply_to_status_id_str": null, "in_reply_to_user_id": null, "in_reply_to_user_id_str": null, "in_reply_to_screen_name": null, "user": {"id": 55539445, "id_str": "55539445", "name": "ravishankar", "screen_name": "ravi_bellur", "location": "", "description": "Son, Husband, Father, Professional, Entrepreneur", "url": null, "entities": {"description": {"urls": []}}, "protected": false, "followers_count": 35, "friends_count": 188, "listed_count": 26, "created_at": "Fri Jul 10 11:47:31 +0000 2009", "favourites_count": 2778, "utc_offset": null, "time_zone": null, "geo_enabled": false, "verified": false, "statuses_count": 1234, "lang": "en", "contributors_enabled": false, "is_translator": false, "is_translation_enabled": false, "profile_background_color": "C0DEED", "profile_background_image_url": "http://abs.twimg.com/images/themes/theme1/bg.png", "profile_background_image_url_https": "https://abs.twimg.com/images/themes/theme1/bg.png", "profile_background_tile": false, "profile_image_url": "http://abs.twimg.com/sticky/default_profile_images/default_profile_normal.png", "profile_image_url_https": "https://abs.twimg.com/sticky/default_profile_images/default_profile_normal.png", "profile_link_color": "1DA1F2", "profile_sidebar_border_color": "C0DEED", "profile_sidebar_fill_color": "DDEEF6", "profile_text_color": "333333", "profile_use_background_image": true, "has_extended_profile": false, "default_profile": true, "default_profile_image": true, "following": false, "follow_request_sent": false, "notifications": false, "translator_type": "none"}, "geo": null, "coordinates": null, "place": null, "contributors": null, "is_quote_status": false, "retweet_count": 0, "favorite_count": 0, "favorited": false, "retweeted": false, "possibly_sensitive": false, "lang": "en"}