{"created_at": "Wed Feb 27 14:47:19 +0000 2019", "id": 1100769353144958977, "id_str": "1100769353144958977", "full_text": "Arundhati Roy accuses Indian Prime Minister Sru Narendra Modi of raking up \u2018manufactured sentiments\u2019 of national pride among the people.\n\nRead for yourself.... https://t.co/NIlh6Ht5pe", "truncated": false, "display_text_range": [0, 183], "entities": {"hashtags": [], "symbols": [], "user_mentions": [], "urls": [{"url": "https://t.co/NIlh6Ht5pe", "expanded_url": "https://www.thehindu.com/news/national/tamil-nadu/pm-pushing-country-into-war-like-situation/article26353967.ece", "display_url": "thehindu.com/news/national/\u2026", "indices": [160, 183]}]}, "metadata": {"iso_language_code": "en", "result_type": "recent"}, "source": "<a href=\"http://www.facebook.com/twitter\" rel=\"nofollow\">Facebook</a>", "in_reply_to_status_id": null, "in_reply_to_status_id_str": null, "in_reply_to_user_id": null, "in_reply_to_user_id_str": null, "in_reply_to_screen_name": null, "user": {"id": 104890630, "id_str": "104890630", "name": "Saber Jazbhay", "screen_name": "jazlaw24", "location": "somewhere  like the wind", "description": "Twitterlocutor to an ongoing dialogue that must take place.", "url": "https://t.co/VtUsNayeL8", "entities": {"url": {"urls": [{"url": "https://t.co/VtUsNayeL8", "expanded_url": "https://twitter.com/jazlaw24", "display_url": "twitter.com/jazlaw24", "indices": [0, 23]}]}, "description": {"urls": []}}, "protected": false, "followers_count": 1082, "friends_count": 575, "listed_count": 11, "created_at": "Thu Jan 14 18:30:10 +0000 2010", "favourites_count": 284, "utc_offset": null, "time_zone": null, "geo_enabled": true, "verified": false, "statuses_count": 34610, "lang": "en", "contributors_enabled": false, "is_translator": false, "is_translation_enabled": false, "profile_background_color": "C6E2EE", "profile_background_image_url": "http://abs.twimg.com/images/themes/theme2/bg.gif", "profile_background_image_url_https": "https://abs.twimg.com/images/themes/theme2/bg.gif", "profile_background_tile": false, "profile_image_url": "http://pbs.twimg.com/profile_images/680009617880018944/UEusb0mb_normal.jpg", "profile_image_url_https": "https://pbs.twimg.com/profile_images/680009617880018944/UEusb0mb_normal.jpg", "profile_banner_url": "https://pbs.twimg.com/profile_banners/104890630/1402545419", "profile_link_color": "1F98C7", "profile_sidebar_border_color": "C6E2EE", "profile_sidebar_fill_color": "DAECF4", "profile_text_color": "663B12", "profile_use_background_image": true, "has_extended_profile": true, "default_profile": false, "default_profile_image": false, "following": false, "follow_request_sent": false, "notifications": false, "translator_type": "none"}, "geo": null, "coordinates": null, "place": null, "contributors": null, "is_quote_status": false, "retweet_count": 0, "favorite_count": 0, "favorited": false, "retweeted": false, "possibly_sensitive": true, "lang": "en"}