{"created_at": "Wed Feb 27 12:03:43 +0000 2019", "id": 1100728181722468354, "id_str": "1100728181722468354", "full_text": "Just heard Rahul Gandhi and others. It is the Congress who has taken the lead to politicise the Pulwama tragedy.", "truncated": false, "display_text_range": [0, 112], "entities": {"hashtags": [], "symbols": [], "user_mentions": [], "urls": []}, "metadata": {"iso_language_code": "en", "result_type": "recent"}, "source": "<a href=\"http://twitter.com/download/android\" rel=\"nofollow\">Twitter for Android</a>", "in_reply_to_status_id": null, "in_reply_to_status_id_str": null, "in_reply_to_user_id": null, "in_reply_to_user_id_str": null, "in_reply_to_screen_name": null, "user": {"id": 1855035565, "id_str": "1855035565", "name": "Ravi Padukone", "screen_name": "rnpadukone", "location": "Bangalore", "description": "Hindu, \u092c\u094d\u0930\u093e\u0939\u094d\u092e\u0923: seeking \u092c\u094d\u0930\u0939\u094d\u092e\u0928\u094d, highest value. \u092d\u0917\u0935\u0926\u094d\u0917\u0940\u0924\u093e, \u0909\u092a\u0928\u093f\u0937\u0926, \u0936\u0902\u0915\u0930 \u092d\u093e\u0937\u094d\u092f\u0964 Sanskrit lang: must master. \u0927\u0930\u094d\u092e:  priority. Defend \u092d\u093e\u0930\u0924\u0940 \u0938\u0902\u0938\u094d\u0915\u0943\u0924\u093f, \u092a\u094d\u0930\u0917\u0924\u093f\u0964", "url": null, "entities": {"description": {"urls": []}}, "protected": false, "followers_count": 399, "friends_count": 404, "listed_count": 34, "created_at": "Wed Sep 11 17:50:29 +0000 2013", "favourites_count": 6269, "utc_offset": null, "time_zone": null, "geo_enabled": true, "verified": false, "statuses_count": 27725, "lang": "en", "contributors_enabled": false, "is_translator": false, "is_translation_enabled": false, "profile_background_color": "C0DEED", "profile_background_image_url": "http://abs.twimg.com/images/themes/theme1/bg.png", "profile_background_image_url_https": "https://abs.twimg.com/images/themes/theme1/bg.png", "profile_background_tile": false, "profile_image_url": "http://pbs.twimg.com/profile_images/453606503472041984/HAyoI5uJ_normal.jpeg", "profile_image_url_https": "https://pbs.twimg.com/profile_images/453606503472041984/HAyoI5uJ_normal.jpeg", "profile_banner_url": "https://pbs.twimg.com/profile_banners/1855035565/1397004561", "profile_link_color": "1DA1F2", "profile_sidebar_border_color": "C0DEED", "profile_sidebar_fill_color": "DDEEF6", "profile_text_color": "333333", "profile_use_background_image": true, "has_extended_profile": true, "default_profile": true, "default_profile_image": false, "following": false, "follow_request_sent": false, "notifications": false, "translator_type": "none"}, "geo": null, "coordinates": null, "place": {"id": "1b8680cd52a711cb", "url": "https://api.twitter.com/1.1/geo/id/1b8680cd52a711cb.json", "place_type": "city", "name": "Bengaluru", "full_name": "Bengaluru, India", "country_code": "IN", "country": "India", "contained_within": [], "bounding_box": {"type": "Polygon", "coordinates": [[[77.373474, 12.919037], [77.739371, 12.919037], [77.739371, 13.231381], [77.373474, 13.231381]]]}, "attributes": {}}, "contributors": null, "is_quote_status": false, "retweet_count": 0, "favorite_count": 1, "favorited": false, "retweeted": false, "lang": "en"}